llama_index/readers/arango_db/__init__.py
llama_index/readers/arango_db/base.py
llama_index_readers_arango_db-0.4.1.dist-info/METADATA
llama_index_readers_arango_db-0.4.1.dist-info/WHEEL
llama_index_readers_arango_db-0.4.1.dist-info/licenses/LICENSE
llama_index_readers_arango_db-0.4.1.dist-info/RECORD
